saas_auth/__init__.py
saas_auth/admin.py
saas_auth/apps.py
saas_auth/saas_permissions.py
saas_auth/settings.py
saas_auth/util.py
saas_auth/api_urls/__init__.py
saas_auth/api_urls/all.py
saas_auth/api_urls/session.py
saas_auth/api_urls/token.py
saas_auth/drf/__init__.py
saas_auth/drf/authentication.py
saas_auth/drf/errors.py
saas_auth/drf/permissions.py
saas_auth/endpoints/__init__.py
saas_auth/endpoints/sessions.py
saas_auth/endpoints/tokens.py
saas_auth/location/__init__.py
saas_auth/location/base.py
saas_auth/location/cloudflare.py
saas_auth/location/geoip2.py
saas_auth/middleware/__init__.py
saas_auth/middleware/session_record.py
saas_auth/migrations/0001_initial.py
saas_auth/migrations/0002_alter_usertoken_scope.py
saas_auth/migrations/__init__.py
saas_auth/models/__init__.py
saas_auth/models/session.py
saas_auth/models/token.py
saas_auth/serializers/__init__.py
saas_auth/serializers/session.py
saas_auth/serializers/token.py
django_saas_auth-0.4.1.dist-info/METADATA
django_saas_auth-0.4.1.dist-info/WHEEL
django_saas_auth-0.4.1.dist-info/RECORD
